<?xml version="1.0" encoding="UTF-8" standalone="yes"?>
<SimObject>
    <simob_variables>
        <entry xmlns:xsi="http://www.w3.org/2001/XMLSchema-instance" xsi:type="myHashMapEntryTypeVector3F" key="position">
            <value>
                <x>0.0</x>
                <y>-2.0</y>
                <z>25.0</z>
            </value>
        </entry>
        <entry xmlns:xsi="http://www.w3.org/2001/XMLSchema-instance" xsi:type="myHashMapEntryTypeObject" key="enabled">
            <value xmlns:xs="http://www.w3.org/2001/XMLSchema" xsi:type="xs:boolean">false</value>
        </entry>
        <entry xmlns:xsi="http://www.w3.org/2001/XMLSchema-instance" xsi:type="myHashMapEntryTypeObject" key="scale">
            <value xmlns:xs="http://www.w3.org/2001/XMLSchema" xsi:type="xs:float">0.1</value>
        </entry>
        <entry xmlns:xsi="http://www.w3.org/2001/XMLSchema-instance" xsi:type="myHashMapEntryTypeObject" key="filepath">
            <value xmlns:xs="http://www.w3.org/2001/XMLSchema" xsi:type="xs:string">pipe/pipe__gate_5meter.obj</value>
        </entry>
        <entry xmlns:xsi="http://www.w3.org/2001/XMLSchema-instance" xsi:type="myHashMapEntryTypeObject" key="icon">
            <value xmlns:xs="http://www.w3.org/2001/XMLSchema" xsi:type="xs:string">testgate.png</value>
        </entry>
        <entry xmlns:xsi="http://www.w3.org/2001/XMLSchema-instance" xsi:type="myHashMapEntryTypeObject" key="dnd_icon">
            <value xmlns:xs="http://www.w3.org/2001/XMLSchema" xsi:type="xs:string">testgate_dnd.png</value>
        </entry>
        <entry xmlns:xsi="http://www.w3.org/2001/XMLSchema-instance" xsi:type="myHashMapEntryTypeObject" key="sonar_detectable">
            <value xmlns:xs="http://www.w3.org/2001/XMLSchema" xsi:type="xs:boolean">true</value>
        </entry>
        <entry xmlns:xsi="http://www.w3.org/2001/XMLSchema-instance" xsi:type="myHashMapEntryTypeHashMap" key="Collision">
            <value>
                <entry xsi:type="myHashMapEntryTypeVector3F" key="collision_position">
                    <value>
                        <x>0.0</x>
                        <y>0.0</y>
                        <z>0.0</z>
                    </value>
                </entry>
                <entry xsi:type="myHashMapEntryTypeVector3F" key="dimensions">
                    <value>
                        <x>1.0</x>
                        <y>1.0</y>
                        <z>1.0</z>
                    </value>
                </entry>
                <entry xsi:type="myHashMapEntryTypeObject" key="type">
                    <value xmlns:xs="http://www.w3.org/2001/XMLSchema" xsi:type="xs:int">0</value>
                </entry>
                <entry xsi:type="myHashMapEntryTypeObject" key="debug_collision">
                    <value xmlns:xs="http://www.w3.org/2001/XMLSchema" xsi:type="xs:boolean">false</value>
                </entry>
                <entry xsi:type="myHashMapEntryTypeObject" key="collidable">
                    <value xmlns:xs="http://www.w3.org/2001/XMLSchema" xsi:type="xs:boolean">false</value>
                </entry>
            </value>
        </entry>
        <entry xmlns:xsi="http://www.w3.org/2001/XMLSchema-instance" xsi:type="myHashMapEntryTypeColorRGBA" key="color">
            <value>
                <a>0.0</a>
                <b>0.0</b>
                <g>1.0</g>
                <r>0.0</r>
            </value>
        </entry>
        <entry xmlns:xsi="http://www.w3.org/2001/XMLSchema-instance" xsi:type="myHashMapEntryTypeVector3F" key="rotation">
            <value>
                <x>1.5707964</x>
                <y>0.0</y>
                <z>0.0</z>
            </value>
        </entry>
        <entry xmlns:xsi="http://www.w3.org/2001/XMLSchema-instance" xsi:type="myHashMapEntryTypeObject" key="name">
            <value xmlns:xs="http://www.w3.org/2001/XMLSchema" xsi:type="xs:string">testgate2</value>
        </entry>
        <entry xmlns:xsi="http://www.w3.org/2001/XMLSchema-instance" xsi:type="myHashMapEntryTypeObject" key="pinger">
            <value xmlns:xs="http://www.w3.org/2001/XMLSchema" xsi:type="xs:boolean">false</value>
        </entry>
        <entry xmlns:xsi="http://www.w3.org/2001/XMLSchema-instance" xsi:type="myHashMapEntryTypeObject" key="light">
            <value xmlns:xs="http://www.w3.org/2001/XMLSchema" xsi:type="xs:boolean">false</value>
        </entry>
    </simob_variables>
</SimObject>
